snekchek/__init__.py
snekchek/__main__.py
snekchek/baseconfig.py
snekchek/config_gen.py
snekchek/format.py
snekchek/lint.py
snekchek/misc.py
snekchek/secure.py
snekchek/structure.py
snekchek/style.py
snekchek/tool.py
snekchek/utils.py
tests/__init__.py
tests/test_dummy.py
snekchek-0.4.8.dist-info/LICENSE
snekchek-0.4.8.dist-info/METADATA
snekchek-0.4.8.dist-info/WHEEL
snekchek-0.4.8.dist-info/entry_points.txt
snekchek-0.4.8.dist-info/top_level.txt
snekchek-0.4.8.dist-info/RECORD
